README.rst
setup.cfg
setup.py
src/pgmanagedconnection/__init__.py
src/pgmanagedconnection/connection.py
src/psycopg2_managed_connection.egg-info/PKG-INFO
src/psycopg2_managed_connection.egg-info/SOURCES.txt
src/psycopg2_managed_connection.egg-info/dependency_links.txt
src/psycopg2_managed_connection.egg-info/not-zip-safe
src/psycopg2_managed_connection.egg-info/pbr.json
src/psycopg2_managed_connection.egg-info/requires.txt
src/psycopg2_managed_connection.egg-info/top_level.txt