Metadata-Version: 1.0
Name: psycopg2-managed-connection
Version: 1.0.0
Summary: Thread-safe connection manager for psycopg2 connections.
Home-page: UNKNOWN
Author: Ted Kaemming, Disqus
Author-email: ted@disqus.com
License: Apache License 2.0
Platform: UNKNOWN
